{"data": {"labels": ["twitter.com", "nova24tv.si", "youtu.be", "fllwrs.com", "siol.net", "www.24ur.com", "www.youtube.com", "www.rtvslo.si", "reporter.si", "www.demokracija.si", "www.facebook.com", "www.casnik.si", "sta.si", "www.dnevnik.si", "www.slovenskenovice.si", "vfokusu.com", "pozareport.si", "www.domovina.je", "www.domovinasospomini.eu", "skrivnostna.si"], "datasets": [{"label": "Lažni profili", "data": [335, 271, 212, 182, 153, 93, 89, 81, 41, 41, 30, 25, 25, 23, 23, 23, 20, 19, 19, 19]}]}}