{"hashtags": [{"label": "vsoboto", "value": 82}, {"label": "covid19", "value": 73}, {"label": "plts", "value": 38}, {"label": "tdf2020", "value": 22}, {"label": "tar\u010da", "value": 20}, {"label": "slovenia", "value": 19}, {"label": "matekejbriketov", "value": 16}, {"label": "maribor", "value": 14}, {"label": "protest", "value": 14}, {"label": "covid_19", "value": 14}, {"label": "izprihodnosti", "value": 13}, {"label": "zbalkonovnakolesa", "value": 12}, {"label": "intervju", "value": 12}, {"label": "sampovem", "value": 11}, {"label": "nivedela", "value": 11}, {"label": "catsoftwitter", "value": 10}, {"label": "princteme", "value": 10}, {"label": "covid\u30fc19", "value": 9}, {"label": "podprimomedije", "value": 9}, {"label": "vsisoisti", "value": 9}], "urls": [{"label": "vecer.com", "value": 3697}, {"label": "reporter.si", "value": 152}, {"label": "nogomania.com", "value": 116}, {"label": "youtu.be", "value": 83}, {"label": "sta.si", "value": 58}, {"label": "rtvslo.si", "value": 55}, {"label": "finance.si", "value": 38}, {"label": "youtube.com", "value": 36}, {"label": "delo.si", "value": 35}, {"label": "24ur.com", "value": 32}, {"label": "dnevnik.si", "value": 26}, {"label": "necenzurirano.si", "value": 21}, {"label": "facebook.com", "value": 17}, {"label": "bit.ly", "value": 16}, {"label": "mladina.si", "value": 14}, {"label": "j.mp", "value": 14}, {"label": "damijan.org", "value": 12}, {"label": "theguardian.com", "value": 11}, {"label": "vipavska.eu", "value": 11}], "retweets": [{"label": "vecer", "value": 1735}, {"label": "UrosEsih", "value": 318}, {"label": "RevijaReporter", "value": 270}, {"label": "welcomet0nature", "value": 249}, {"label": "BlazBFK", "value": 238}, {"label": "mihadajcman", "value": 151}, {"label": "SpletnaMladina", "value": 147}, {"label": "ZanaVertacnik", "value": 116}, {"label": "MatijaStepisnik", "value": 115}, {"label": "Nogomania", "value": 110}, {"label": "Matej_Klaric", "value": 94}, {"label": "STA_novice", "value": 73}, {"label": "petrasovdat", "value": 72}, {"label": "p_zoran", "value": 71}, {"label": "cctv_idiots", "value": 71}, {"label": "dreychee", "value": 61}, {"label": "VanessaCokl", "value": 60}, {"label": "FranciKek", "value": 55}, {"label": "rose_roseae", "value": 54}, {"label": "dodo", "value": 54}]}