{"hashtags": [{"label": "\u017eilneopornice", "value": 97}, {"label": "neonnettle", "value": 25}, {"label": "video", "value": 21}, {"label": "covid19", "value": 16}, {"label": "gotofajonkaje", "value": 13}, {"label": "po\u017eareport", "value": 11}, {"label": "slovenija", "value": 11}, {"label": "sampra\u0161am", "value": 8}, {"label": "politika", "value": 8}, {"label": "ostanizdrav", "value": 7}, {"label": "sampovem", "value": 7}, {"label": "koronavirus", "value": 7}, {"label": "foto", "value": 7}, {"label": "anonymousnews", "value": 6}, {"label": "zeitgeist", "value": 6}, {"label": "ivanretvita", "value": 5}, {"label": "irannlbgate", "value": 5}, {"label": "yugoslav", "value": 5}, {"label": "slovenia", "value": 5}, {"label": "covid_19", "value": 4}], "urls": [{"label": "nova24tv.si", "value": 619}, {"label": "facebook.com", "value": 486}, {"label": "disq.us", "value": 257}, {"label": "siol.net", "value": 218}, {"label": "demokracija.si", "value": 213}, {"label": "youtube.com", "value": 174}, {"label": "youtu.be", "value": 114}, {"label": "reporter.si", "value": 113}, {"label": "rtvslo.si", "value": 99}, {"label": "fllwrs.com", "value": 70}, {"label": "24ur.com", "value": 65}, {"label": "domovina.je", "value": 53}, {"label": "vfokusu.com", "value": 46}, {"label": "portalplus.si", "value": 41}, {"label": "pozareport.si", "value": 39}, {"label": "casnik.si", "value": 38}, {"label": "slovenskenovice.si", "value": 36}, {"label": "e-maribor.si", "value": 30}, {"label": "delo.si", "value": 30}], "retweets": [{"label": "zeljko_novak", "value": 478}, {"label": "JJansaSDS", "value": 76}, {"label": "vinkovasle1", "value": 57}, {"label": "DrustvoHudajama", "value": 54}, {"label": "GPreac", "value": 53}, {"label": "BojanPozar", "value": 53}, {"label": "Jo_AnnaOfArt", "value": 50}, {"label": "JakaDolinar2", "value": 45}, {"label": "cikibucka", "value": 42}, {"label": "vladaRS", "value": 32}, {"label": "Nova24TV", "value": 31}, {"label": "tomltoml", "value": 30}, {"label": "mrevlje", "value": 30}, {"label": "Bond00775328617", "value": 28}, {"label": "peterjancic", "value": 27}, {"label": "DKopse", "value": 25}, {"label": "SergijVermiglio", "value": 24}, {"label": "Demokracija1", "value": 23}, {"label": "JozeBiscak", "value": 22}, {"label": "ZigaTurk", "value": 22}]}