{"hashtags": [{"label": "ostanidoma", "value": 5}, {"label": "sarcasmoff", "value": 3}, {"label": "prioritete", "value": 3}, {"label": "malazloba", "value": 3}, {"label": "srcebije", "value": 2}, {"label": "samopovem", "value": 2}, {"label": "pohvalanadan", "value": 2}, {"label": "flatearth", "value": 1}, {"label": "westworld", "value": 1}, {"label": "ninamedia", "value": 1}, {"label": "helpbiden", "value": 1}, {"label": "baller", "value": 1}, {"label": "yamaha", "value": 1}, {"label": "belledelphine", "value": 1}, {"label": "snookerworldchampionship", "value": 1}, {"label": "crucible", "value": 1}, {"label": "plm", "value": 1}, {"label": "ceferin", "value": 1}, {"label": "var", "value": 1}, {"label": "fightcamp", "value": 1}], "urls": [{"label": "youtu.be", "value": 16}, {"label": "nova24tv.si", "value": 5}, {"label": "facebook.com", "value": 4}, {"label": "24ur.com", "value": 4}, {"label": "politico.eu", "value": 3}, {"label": "svet24.si", "value": 2}, {"label": "sledilnik.org", "value": 2}, {"label": "siol.net", "value": 2}, {"label": "finance.si", "value": 2}, {"label": "domovina.je", "value": 2}, {"label": "rtvslo.si", "value": 2}, {"label": "youtube.com", "value": 2}, {"label": "bbc.com", "value": 1}, {"label": "europa.eu", "value": 1}, {"label": "rs-rs.si", "value": 1}, {"label": "ucsf.edu", "value": 1}, {"label": "infranken.de", "value": 1}, {"label": "mojepodravje.si", "value": 1}, {"label": "1.SV", "value": 1}], "retweets": [{"label": "kratkazgodba", "value": 6}, {"label": "LajnarEU", "value": 5}, {"label": "AnaOstricki", "value": 5}, {"label": "FriedrichHayek", "value": 4}, {"label": "kricac", "value": 4}, {"label": "seba1337", "value": 4}, {"label": "mrevlje", "value": 4}, {"label": "suzana1955", "value": 3}, {"label": "petrasovdat", "value": 3}, {"label": "had", "value": 2}, {"label": "rose_roseae", "value": 2}, {"label": "bojan_krajnc", "value": 2}, {"label": "dallasmavs", "value": 2}, {"label": "GreenPlusAnE", "value": 2}, {"label": "barjanski", "value": 2}, {"label": "SafetAlibeg", "value": 2}, {"label": "zasledovalec70", "value": 2}, {"label": "LapSaso", "value": 2}, {"label": "FranciKek", "value": 2}, {"label": "milijonar", "value": 2}]}