{"hashtags": [{"label": "iusinfo", "value": 195}, {"label": "koronavirus", "value": 97}, {"label": "izbori2020", "value": 46}, {"label": "prvasmjena", "value": 35}, {"label": "cepci", "value": 26}, {"label": "hrvatska", "value": 24}, {"label": "p\u011btadvac\u00edtka", "value": 19}, {"label": "covid19", "value": 15}, {"label": "gospodarstvo", "value": 15}, {"label": "turizam", "value": 15}, {"label": "zagreb", "value": 14}, {"label": "dnevnikhtv", "value": 11}, {"label": "nijz", "value": 11}, {"label": "bmw", "value": 10}, {"label": "potres", "value": 10}, {"label": "tiktok", "value": 9}, {"label": "mffl", "value": 8}, {"label": "\u0161kola", "value": 7}, {"label": "nba", "value": 7}, {"label": "izborihr", "value": 6}], "urls": [{"label": "hrt.hr", "value": 3743}, {"label": "bit.ly", "value": 3168}, {"label": "telegram.hr", "value": 2114}, {"label": "iusinfo.si", "value": 277}, {"label": "drzavljank.si", "value": 226}, {"label": "youtu.be", "value": 55}, {"label": "mfcr.cz", "value": 26}, {"label": "fllwrs.com", "value": 26}, {"label": "nova24tv.si", "value": 24}, {"label": "24ur.com", "value": 21}, {"label": "youtube.com", "value": 20}, {"label": "siol.net", "value": 16}, {"label": "tiktok.com", "value": 15}, {"label": "slovenskenovice.si", "value": 15}, {"label": "rtvslo.si", "value": 13}, {"label": "necenzurirano.si", "value": 11}, {"label": "domovina.je", "value": 9}, {"label": "publishwall.si", "value": 9}, {"label": "delo.si", "value": 8}], "retweets": [{"label": "DrzavljanK", "value": 154}, {"label": "paps_auto", "value": 34}, {"label": "__MPower__", "value": 30}, {"label": "MinFinCZ", "value": 29}, {"label": "Domovina_je", "value": 25}, {"label": "AndrejBabis", "value": 16}, {"label": "financnisprava", "value": 16}, {"label": "GPreac", "value": 16}, {"label": "BMWMotorsport", "value": 12}, {"label": "SosicDajana", "value": 9}, {"label": "Sportinfosi", "value": 9}, {"label": "AuschwitzMuseum", "value": 9}, {"label": "SeverMaja", "value": 8}, {"label": "TheFigen", "value": 7}, {"label": "HRTsport", "value": 7}, {"label": "bmz9453", "value": 7}, {"label": "SignsFun", "value": 7}, {"label": "Ffs_OMG", "value": 7}, {"label": "RobertDeNiroUS", "value": 6}, {"label": "OtsileJT", "value": 6}]}