{"hashtags": [{"label": "trol", "value": 46}, {"label": "corrupt", "value": 24}, {"label": "kafetarime", "value": 18}, {"label": "\u0161c", "value": 17}, {"label": "auschwitz", "value": 16}, {"label": "tvitertura", "value": 16}, {"label": "juventus", "value": 15}, {"label": "giveaway", "value": 14}, {"label": "covid19", "value": 13}, {"label": "kletnaplesen", "value": 13}, {"label": "juvahead", "value": 12}, {"label": "onokad", "value": 12}, {"label": "klet", "value": 10}, {"label": "finoallafine", "value": 9}, {"label": "tiktak", "value": 9}, {"label": "slovenia", "value": 8}, {"label": "juvahead360", "value": 7}, {"label": "tar\u010da", "value": 7}, {"label": "smrtjan\u0161izmu", "value": 7}, {"label": "forzajuve", "value": 6}], "urls": [{"label": "youtu.be", "value": 172}, {"label": "fllwrs.com", "value": 75}, {"label": "youtube.com", "value": 32}, {"label": "instagram.com", "value": 28}, {"label": "runda.si", "value": 26}, {"label": "dnevnik.si", "value": 20}, {"label": "rtvslo.si", "value": 19}, {"label": "vecer.com", "value": 17}, {"label": "24ur.com", "value": 14}, {"label": "gregorblog.com", "value": 14}, {"label": "cyclingnews.com", "value": 13}, {"label": "necenzurirano.si", "value": 12}, {"label": "wikipedia.org", "value": 10}, {"label": "t.me", "value": 10}, {"label": "wn.nr", "value": 10}, {"label": "delo.si", "value": 9}, {"label": "facebook.com", "value": 9}, {"label": "nova.rs", "value": 9}, {"label": "vezjak.com", "value": 8}], "retweets": [{"label": "blaz_zgaga", "value": 46}, {"label": "had", "value": 33}, {"label": "AuschwitzMuseum", "value": 33}, {"label": "dreychee", "value": 24}, {"label": "ciro_ciril", "value": 23}, {"label": "rose_roseae", "value": 21}, {"label": "KilgoreSH5", "value": 21}, {"label": "meteoriterain", "value": 21}, {"label": "stanka_d", "value": 21}, {"label": "necenzurirano_", "value": 20}, {"label": "badabumbadabum", "value": 19}, {"label": "MatejaZvizej1", "value": 18}, {"label": "insajder_com", "value": 18}, {"label": "DrzavljanD", "value": 17}, {"label": "juvandme", "value": 16}, {"label": "juventusfc", "value": 16}, {"label": "AntonPeinkiher", "value": 15}, {"label": "chadloder", "value": 15}, {"label": "ContinassaMech", "value": 14}, {"label": "SpletnaMladina", "value": 14}]}